Source/design/module_bcd_decoder.sv
module module_bcd_decoder(input logic [3:0] w, output logic [6:0] bcd);
    assign bcd[6] = w[1] | w[3] | (~w[2] & ~w[0]) | (w[2] & w[0]);   // a
    assign bcd[5] = ~w[2] | w[1] | ~w[0];                    // b
    assign bcd[4] = ~w[1] | w[2] | w[0];                      // c
    assign bcd[3] = (~w[2] & ~w[0]) | (~w[2] & w[1]) + (w[1] & ~w[0]) | (w[2] & ~w[1] & w[0]) ;  // d
    assign bcd[2] = (~w[2] & ~w[0]) | (w[1] & ~w[0]);         // e
    assign bcd[1] = w[3] | (~w[1] & ~w[0]) | (w[2] & ~w[1]);  // f
    assign bcd[0] = w[3] | (~w[2] & w[1]) | (w[2] & ~w[0]) | (w[2] & ~w[1]);  // g
endmodule

Source/sim/module_bcd_decoder_tb.sv
`timescale 1ns/1ps

module module_bcd_decoder_tb;
    logic [3:0] w;         // Señal de entrada
    logic [6:0] bcd;      // Señal de salida

    // Instanciamos el módulo 'module_bcd_syndrome'
    module_bcd_decoder uut (.w(w), .bcd(bcd));

    initial begin
        // 0
        w = 4'b0000; #10;
        $display("Number: %b, Segments: %b", w, bcd);
        
        // 1
        w = 4'b0001; #10;
        $display("Number: %b, Segments: %b", w, bcd);

        // 2
        w = 4'b0010; #10;
        $display("Number: %b, Segments: %b", w, bcd);

        // 3
        w = 4'b0011; #10;
        $display("Number: %b, Segments: %b", w, bcd);

        // 4
        w = 4'b0100; #10;
        $display("Number: %b, Segments: %b", w, bcd);

        // 5
        w = 4'b0101; #10;
        $display("Number: %b, Segments: %b", w, bcd);
        

        // 6
        w = 4'b0110; #10;
        $display("Number: %b, Segments: %b", w, bcd);
        
        // 7
        w = 4'b0111; #10;
        $display("Number: %b, Segments: %b", w, bcd);

        // 8
        w = 4'b1000; #10;
        $display("Number: %b, Segments: %b", w, bcd);

        // 9
        w = 4'b1001; #10;
        $display("Number: %b, Segments: %b", w, bcd);
    end

    initial begin
        // Guardar el archivo de simulación en formato VCD
        $dumpfile("module_bcd_decoder_tb.vcd");
        $dumpvars(0, module_bcd_decoder_tb);  // Nombre correcto del módulo de prueba
    end
endmodule

Source/build/module_bcd_decoder_tb.vcd
$date
	Sat Mar 22 23:17:05 2025
$end
$version
	Icarus Verilog
$end
$timescale
	1ps
$end
$scope module module_bcd_decoder_tb $end
$var wire 7 ! bcd [6:0] $end
$var reg 4 " w [3:0] $end
$scope module uut $end
$var wire 4 # w [3:0] $end
$var wire 7 $ bcd [6:0] $end
$upscope $end
$upscope $end
$enddefinitions $end
$comment Show the parameter values. $end
$dumpall
$end
#0
$dumpvars
b1111110 $
b0 #
b0 "
b1111110 !
$end
#10000
b110000 !
b110000 $
b1 "
b1 #
#20000
b1101101 !
b1101101 $
b10 "
b10 #
#30000
b1111001 !
b1111001 $
b11 "
b11 #
#40000
b110011 !
b110011 $
b100 "
b100 #
#50000
b1011011 !
b1011011 $
b101 "
b101 #
#60000
b1111101 !
b1111101 $
b110 "
b110 #
#70000
b1110000 !
b1110000 $
b111 "
b111 #
#80000
b1111111 !
b1111111 $
b1000 "
b1000 #
#90000
b1110011 !
b1110011 $
b1001 "
b1001 #
